LICENSE
MANIFEST.in
README.rst
setup.py
django_admin_hstore/__init__.py
django_admin_hstore/widgets.py
django_admin_hstore.egg-info/PKG-INFO
django_admin_hstore.egg-info/SOURCES.txt
django_admin_hstore.egg-info/dependency_links.txt
django_admin_hstore.egg-info/not-zip-safe
django_admin_hstore.egg-info/requires.txt
django_admin_hstore.egg-info/top_level.txt
django_admin_hstore/static/admin/js/django_admin_hstore/bundles/reactHStore.js
django_admin_hstore/templates/django_admin_hstore/hstore_widget.html
django_admin_hstore/templatetags/__init__.py
django_admin_hstore/templatetags/jsonify.py